README.md
requirements.txt
setup.py
chainer_finetune.egg-info/PKG-INFO
chainer_finetune.egg-info/SOURCES.txt
chainer_finetune.egg-info/dependency_links.txt
chainer_finetune.egg-info/not-zip-safe
chainer_finetune.egg-info/requires.txt
chainer_finetune.egg-info/top_level.txt
finetune/__init__.py
finetune/classifier.py
finetune/dataset.py
finetune/parser.py
finetune/finetuner/__init__.py
finetune/finetuner/base.py
finetune/finetuner/mpi.py
finetune/training/__init__.py
finetune/training/trainer.py