Metadata-Version: 1.2
Name: chainer-finetune
Version: 0.2.0
Summary: Fine-tune framework based on chainer
Home-page: UNKNOWN
Author: Dimitri Korsch
Author-email: korschdima@gmail.com
License: MIT License
Platform: UNKNOWN
Requires-Python: >3.5
